<?xml version="1.0"?>
<rdf:RDF xmlns="http://semanticscience.org/ontology/sio.owl#"
     xml:base="http://semanticscience.org/ontology/sio.owl"
     xmlns:rdf="http://www.w3.org/1999/02/22-rdf-syntax-ns#"
     xmlns:terms="http://purl.org/dc/terms/"
     xmlns:owl="http://www.w3.org/2002/07/owl#"
     xmlns:resource="http://semanticscience.org/resource/"
     xmlns:xml="http://www.w3.org/XML/1998/namespace"
     xmlns:xsd="http://www.w3.org/2001/XMLSchema#"
     xmlns:rdfs="http://www.w3.org/2000/01/rdf-schema#">
    <owl:Ontology rdf:about="http://semanticscience.org/ontology/sio.owl">
        <owl:versionIRI rdf:resource="http://semanticscience.org/ontology/sio/v1.43/sio-subset-emotion.owl"/>
    </owl:Ontology>
    


    <!-- 
    ///////////////////////////////////////////////////////////////////////////////////////
    //
    // Annotation properties
    //
    ///////////////////////////////////////////////////////////////////////////////////////
     -->


    


    <!-- http://purl.org/dc/terms/description -->


    <owl:AnnotationProperty rdf:about="http://purl.org/dc/terms/description"/>
    


    <!-- http://semanticscience.org/resource/hasSynonym -->


    <owl:AnnotationProperty rdf:about="http://semanticscience.org/resource/hasSynonym"/>
    


    <!-- http://semanticscience.org/resource/subset -->


    <owl:AnnotationProperty rdf:about="http://semanticscience.org/resource/subset"/>
    


    <!-- 
    ///////////////////////////////////////////////////////////////////////////////////////
    //
    // Classes
    //
    ///////////////////////////////////////////////////////////////////////////////////////
     -->


    


    <!-- http://semanticscience.org/resource/SIO_000000 -->


    <owl:Class rdf:about="http://semanticscience.org/resource/SIO_000000">
        <terms:description xml:lang="en">Every thing is an entity.</terms:description>
        <resource:subset rdf:datatype="http://www.w3.org/2001/XMLSchema#string">core</resource:subset>
        <rdfs:isDefinedBy rdf:resource="http://semanticscience.org/ontology/sio/v1.43/sio-subset-emotion.owl"/>
        <rdfs:label xml:lang="en">entity</rdfs:label>
    </owl:Class>
    


    <!-- http://semanticscience.org/resource/SIO_000006 -->


    <owl:Class rdf:about="http://semanticscience.org/resource/SIO_000006">
        <rdfs:subClassOf rdf:resource="http://semanticscience.org/resource/SIO_000000"/>
        <terms:description xml:lang="en">A process is an entity that is identifiable only through the unfolding of time, has temporal parts, and unless otherwise specified/predicted, cannot be identified from any instant of time in which it exists.</terms:description>
        <resource:subset rdf:datatype="http://www.w3.org/2001/XMLSchema#string">core</resource:subset>
        <resource:subset rdf:datatype="http://www.w3.org/2001/XMLSchema#string">process+</resource:subset>
        <rdfs:isDefinedBy rdf:resource="http://semanticscience.org/ontology/sio/v1.43/sio-subset-emotion.owl"/>
        <rdfs:label xml:lang="en">process</rdfs:label>
    </owl:Class>
    


    <!-- http://semanticscience.org/resource/SIO_000276 -->


    <owl:Class rdf:about="http://semanticscience.org/resource/SIO_000276">
        <rdfs:subClassOf rdf:resource="http://semanticscience.org/resource/SIO_001195"/>
        <terms:description xml:lang="en">An emotion is a process (experience) that arises internally or from an involuntary physiological response to a stimulus.</terms:description>
        <resource:subset rdf:datatype="http://www.w3.org/2001/XMLSchema#string">emotion++</resource:subset>
        <rdfs:isDefinedBy rdf:resource="http://semanticscience.org/ontology/sio/v1.43/sio-subset-emotion.owl"/>
        <rdfs:label xml:lang="en">emotion</rdfs:label>
    </owl:Class>
    


    <!-- http://semanticscience.org/resource/SIO_000358 -->


    <owl:Class rdf:about="http://semanticscience.org/resource/SIO_000358">
        <rdfs:subClassOf rdf:resource="http://semanticscience.org/resource/SIO_000825"/>
        <terms:description xml:lang="en">intent is a desire to realize a particular outcome.</terms:description>
        <rdfs:isDefinedBy rdf:resource="http://semanticscience.org/ontology/sio/v1.43/sio-subset-emotion.owl"/>
        <rdfs:label xml:lang="en">intent</rdfs:label>
    </owl:Class>
    


    <!-- http://semanticscience.org/resource/SIO_000410 -->


    <owl:Class rdf:about="http://semanticscience.org/resource/SIO_000410">
        <rdfs:subClassOf rdf:resource="http://semanticscience.org/resource/SIO_000828"/>
        <terms:description xml:lang="en">anger is disgust directed toward an equal status individual.</terms:description>
        <rdfs:isDefinedBy rdf:resource="http://semanticscience.org/ontology/sio/v1.43/sio-subset-emotion.owl"/>
        <rdfs:label xml:lang="en">anger</rdfs:label>
    </owl:Class>
    


    <!-- http://semanticscience.org/resource/SIO_000411 -->


    <owl:Class rdf:about="http://semanticscience.org/resource/SIO_000411">
        <rdfs:subClassOf rdf:resource="http://semanticscience.org/resource/SIO_000828"/>
        <terms:description xml:lang="en">Hate is a deep and emotional extreme dislike, directed against a certain object or class of objects. </terms:description>
        <rdfs:isDefinedBy rdf:resource="http://semanticscience.org/ontology/sio/v1.43/sio-subset-emotion.owl"/>
        <rdfs:label xml:lang="en">hate</rdfs:label>
    </owl:Class>
    


    <!-- http://semanticscience.org/resource/SIO_000412 -->


    <owl:Class rdf:about="http://semanticscience.org/resource/SIO_000412">
        <rdfs:subClassOf rdf:resource="http://semanticscience.org/resource/SIO_000831"/>
        <terms:description xml:lang="en">love is an emotion of a strong affection and personal attachment.</terms:description>
        <rdfs:isDefinedBy rdf:resource="http://semanticscience.org/ontology/sio/v1.43/sio-subset-emotion.owl"/>
        <rdfs:label xml:lang="en">love</rdfs:label>
    </owl:Class>
    


    <!-- http://semanticscience.org/resource/SIO_000812 -->


    <owl:Class rdf:about="http://semanticscience.org/resource/SIO_000812">
        <rdfs:subClassOf rdf:resource="http://semanticscience.org/resource/SIO_000831"/>
        <terms:description xml:lang="en">affection is an emotion characterized with a feeling or type of love for another living thing.</terms:description>
        <rdfs:isDefinedBy rdf:resource="http://semanticscience.org/ontology/sio/v1.43/sio-subset-emotion.owl"/>
        <rdfs:label xml:lang="en">affection</rdfs:label>
    </owl:Class>
    


    <!-- http://semanticscience.org/resource/SIO_000813 -->


    <owl:Class rdf:about="http://semanticscience.org/resource/SIO_000813">
        <rdfs:subClassOf rdf:resource="http://semanticscience.org/resource/SIO_000815"/>
        <terms:description xml:lang="en">angst is the intense feeling of apprehension, anxiety or inner turmoil.</terms:description>
        <rdfs:isDefinedBy rdf:resource="http://semanticscience.org/ontology/sio/v1.43/sio-subset-emotion.owl"/>
        <rdfs:label xml:lang="en">angst</rdfs:label>
    </owl:Class>
    


    <!-- http://semanticscience.org/resource/SIO_000814 -->


    <owl:Class rdf:about="http://semanticscience.org/resource/SIO_000814">
        <rdfs:subClassOf rdf:resource="http://semanticscience.org/resource/SIO_000832"/>
        <terms:description xml:lang="en">Annoyance is an unpleasant emtion that is characterized by a abnormal or excessive sensitivity to some external stimulus.</terms:description>
        <rdfs:isDefinedBy rdf:resource="http://semanticscience.org/ontology/sio/v1.43/sio-subset-emotion.owl"/>
        <rdfs:label xml:lang="en">annoyance</rdfs:label>
    </owl:Class>
    


    <!-- http://semanticscience.org/resource/SIO_000815 -->


    <owl:Class rdf:about="http://semanticscience.org/resource/SIO_000815">
        <rdfs:subClassOf rdf:resource="http://semanticscience.org/resource/SIO_000949"/>
        <terms:description xml:lang="en">anxiety is an emotion charactersized by intense feeling of fear and concern coupled with a physical response.</terms:description>
        <rdfs:isDefinedBy rdf:resource="http://semanticscience.org/ontology/sio/v1.43/sio-subset-emotion.owl"/>
        <rdfs:label xml:lang="en">anxiety</rdfs:label>
    </owl:Class>
    


    <!-- http://semanticscience.org/resource/SIO_000816 -->


    <owl:Class rdf:about="http://semanticscience.org/resource/SIO_000816">
        <rdfs:subClassOf rdf:resource="http://semanticscience.org/resource/SIO_000847"/>
        <terms:description xml:lang="en">apathy is an emotion characterized by lack of interest, enthusiasm, or concern.</terms:description>
        <rdfs:isDefinedBy rdf:resource="http://semanticscience.org/ontology/sio/v1.43/sio-subset-emotion.owl"/>
        <rdfs:label xml:lang="en">apathy</rdfs:label>
    </owl:Class>
    


    <!-- http://semanticscience.org/resource/SIO_000817 -->


    <owl:Class rdf:about="http://semanticscience.org/resource/SIO_000817">
        <rdfs:subClassOf rdf:resource="http://semanticscience.org/resource/SIO_000831"/>
        <terms:description xml:lang="en">arousal is an emotion characterized by state of reactive to stimuli. It involves the activation of the reticular activating system in the brain stem, the autonomic nervous system and the endocrine system, leading to increased heart rate and blood pressure and a condition of sensory alertness, mobility and readiness to respond.</terms:description>
        <rdfs:isDefinedBy rdf:resource="http://semanticscience.org/ontology/sio/v1.43/sio-subset-emotion.owl"/>
        <rdfs:label xml:lang="en">arousal</rdfs:label>
    </owl:Class>
    


    <!-- http://semanticscience.org/resource/SIO_000818 -->


    <owl:Class rdf:about="http://semanticscience.org/resource/SIO_000818">
        <rdfs:subClassOf rdf:resource="http://semanticscience.org/resource/SIO_000831"/>
        <terms:description xml:lang="en">awe is an emotion produced by that which is grand, sublime or powerful and is characterized by a combination of joy, fear and admiration/reverence/respect. </terms:description>
        <rdfs:isDefinedBy rdf:resource="http://semanticscience.org/ontology/sio/v1.43/sio-subset-emotion.owl"/>
        <rdfs:label xml:lang="en">awe</rdfs:label>
    </owl:Class>
    


    <!-- http://semanticscience.org/resource/SIO_000819 -->


    <owl:Class rdf:about="http://semanticscience.org/resource/SIO_000819">
        <rdfs:subClassOf rdf:resource="http://semanticscience.org/resource/SIO_000831"/>
        <terms:description xml:lang="en">boldness is the trait of being willing to undertake things that involve risk or danger.</terms:description>
        <rdfs:isDefinedBy rdf:resource="http://semanticscience.org/ontology/sio/v1.43/sio-subset-emotion.owl"/>
        <rdfs:label xml:lang="en">boldness</rdfs:label>
    </owl:Class>
    


    <!-- http://semanticscience.org/resource/SIO_000820 -->


    <owl:Class rdf:about="http://semanticscience.org/resource/SIO_000820">
        <rdfs:subClassOf rdf:resource="http://semanticscience.org/resource/SIO_000832"/>
        <terms:description xml:lang="en">boredom is the emotion experience by those not interested in their surroundings or available activities.</terms:description>
        <rdfs:isDefinedBy rdf:resource="http://semanticscience.org/ontology/sio/v1.43/sio-subset-emotion.owl"/>
        <rdfs:label xml:lang="en">boredom</rdfs:label>
    </owl:Class>
    


    <!-- http://semanticscience.org/resource/SIO_000821 -->


    <owl:Class rdf:about="http://semanticscience.org/resource/SIO_000821">
        <rdfs:subClassOf rdf:resource="http://semanticscience.org/resource/SIO_000828"/>
        <terms:description xml:lang="en">contempt is disgust towards a lower status individual.</terms:description>
        <rdfs:isDefinedBy rdf:resource="http://semanticscience.org/ontology/sio/v1.43/sio-subset-emotion.owl"/>
        <rdfs:label xml:lang="en">contempt</rdfs:label>
    </owl:Class>
    


    <!-- http://semanticscience.org/resource/SIO_000822 -->


    <owl:Class rdf:about="http://semanticscience.org/resource/SIO_000822">
        <rdfs:subClassOf rdf:resource="http://semanticscience.org/resource/SIO_000840"/>
        <terms:description xml:lang="en">contentment is an emotion characterized by acknowledgement and satisfaction of the current state of affairs.</terms:description>
        <rdfs:isDefinedBy rdf:resource="http://semanticscience.org/ontology/sio/v1.43/sio-subset-emotion.owl"/>
        <rdfs:label xml:lang="en">contentment</rdfs:label>
    </owl:Class>
    


    <!-- http://semanticscience.org/resource/SIO_000823 -->


    <owl:Class rdf:about="http://semanticscience.org/resource/SIO_000823">
        <rdfs:subClassOf rdf:resource="http://semanticscience.org/resource/SIO_000825"/>
        <terms:description xml:lang="en">curiosity is the strong desire to know or learn something.</terms:description>
        <rdfs:isDefinedBy rdf:resource="http://semanticscience.org/ontology/sio/v1.43/sio-subset-emotion.owl"/>
        <rdfs:label xml:lang="en">curiosity</rdfs:label>
    </owl:Class>
    


    <!-- http://semanticscience.org/resource/SIO_000824 -->


    <owl:Class rdf:about="http://semanticscience.org/resource/SIO_000824">
        <rdfs:subClassOf rdf:resource="http://semanticscience.org/resource/SIO_000863"/>
        <terms:description xml:lang="en">depression is an unpleasant emotion linked to aversion to activity that can affect a person&apos;s thoughts, behavior, feelings and physical well-being. Depressed individuals may feel sad, anxious, empty, hopeless, worried, helpless, worthless, guilty, irritable, or restless.</terms:description>
        <resource:hasSynonym rdf:datatype="http://www.w3.org/2001/XMLSchema#string">depressed</resource:hasSynonym>
        <rdfs:isDefinedBy rdf:resource="http://semanticscience.org/ontology/sio/v1.43/sio-subset-emotion.owl"/>
        <rdfs:label xml:lang="en">depression</rdfs:label>
    </owl:Class>
    


    <!-- http://semanticscience.org/resource/SIO_000825 -->


    <owl:Class rdf:about="http://semanticscience.org/resource/SIO_000825">
        <rdfs:subClassOf rdf:resource="http://semanticscience.org/resource/SIO_000848"/>
        <terms:description xml:lang="en">desire is a strong emotion of wanting to have something or wishing for something to happen.</terms:description>
        <rdfs:isDefinedBy rdf:resource="http://semanticscience.org/ontology/sio/v1.43/sio-subset-emotion.owl"/>
        <rdfs:label xml:lang="en">desire</rdfs:label>
    </owl:Class>
    


    <!-- http://semanticscience.org/resource/SIO_000826 -->


    <owl:Class rdf:about="http://semanticscience.org/resource/SIO_000826">
        <rdfs:subClassOf rdf:resource="http://semanticscience.org/resource/SIO_000863"/>
        <terms:description xml:lang="en">despair is depression, hopelessness or lack of hope.</terms:description>
        <rdfs:isDefinedBy rdf:resource="http://semanticscience.org/ontology/sio/v1.43/sio-subset-emotion.owl"/>
        <rdfs:label xml:lang="en">despair</rdfs:label>
    </owl:Class>
    


    <!-- http://semanticscience.org/resource/SIO_000827 -->


    <owl:Class rdf:about="http://semanticscience.org/resource/SIO_000827">
        <rdfs:subClassOf rdf:resource="http://semanticscience.org/resource/SIO_000832"/>
        <terms:description xml:lang="en">disappointment is the feeling of dissatisfaction that follows the failure of expectations or hopes to manifest.</terms:description>
        <resource:hasSynonym rdf:datatype="http://www.w3.org/2001/XMLSchema#string">disappointed</resource:hasSynonym>
        <resource:hasSynonym rdf:datatype="http://www.w3.org/2001/XMLSchema#string">disappointing</resource:hasSynonym>
        <rdfs:isDefinedBy rdf:resource="http://semanticscience.org/ontology/sio/v1.43/sio-subset-emotion.owl"/>
        <rdfs:label xml:lang="en">disappointment</rdfs:label>
    </owl:Class>
    


    <!-- http://semanticscience.org/resource/SIO_000828 -->


    <owl:Class rdf:about="http://semanticscience.org/resource/SIO_000828">
        <rdfs:subClassOf rdf:resource="http://semanticscience.org/resource/SIO_000844"/>
        <terms:description xml:lang="en">Disgust is a feeling of revulsion or profound disapproval aroused by something unpleasant or offensive.</terms:description>
        <rdfs:isDefinedBy rdf:resource="http://semanticscience.org/ontology/sio/v1.43/sio-subset-emotion.owl"/>
        <rdfs:label xml:lang="en">disgust</rdfs:label>
    </owl:Class>
    


    <!-- http://semanticscience.org/resource/SIO_000829 -->


    <owl:Class rdf:about="http://semanticscience.org/resource/SIO_000829">
        <rdfs:subClassOf rdf:resource="http://semanticscience.org/resource/SIO_000837"/>
        <terms:description xml:lang="en">dread is the instense negative emotion that induces fear and apprehension.</terms:description>
        <rdfs:isDefinedBy rdf:resource="http://semanticscience.org/ontology/sio/v1.43/sio-subset-emotion.owl"/>
        <rdfs:label xml:lang="en">dread</rdfs:label>
    </owl:Class>
    


    <!-- http://semanticscience.org/resource/SIO_000830 -->


    <owl:Class rdf:about="http://semanticscience.org/resource/SIO_000830">
        <rdfs:subClassOf rdf:resource="http://semanticscience.org/resource/SIO_000831"/>
        <terms:description xml:lang="en">ecstacy is an emotion characterized by a heightened state of consciousness with total involvement of a subject.</terms:description>
        <rdfs:isDefinedBy rdf:resource="http://semanticscience.org/ontology/sio/v1.43/sio-subset-emotion.owl"/>
        <rdfs:label xml:lang="en">ecstasy</rdfs:label>
    </owl:Class>
    


    <!-- http://semanticscience.org/resource/SIO_000831 -->


    <owl:Class rdf:about="http://semanticscience.org/resource/SIO_000831">
        <rdfs:subClassOf rdf:resource="http://semanticscience.org/resource/SIO_000276"/>
        <terms:description xml:lang="en">A positive emotion is an emotion that feels good.</terms:description>
        <rdfs:isDefinedBy rdf:resource="http://semanticscience.org/ontology/sio/v1.43/sio-subset-emotion.owl"/>
        <rdfs:label xml:lang="en">positive emotion</rdfs:label>
    </owl:Class>
    


    <!-- http://semanticscience.org/resource/SIO_000832 -->


    <owl:Class rdf:about="http://semanticscience.org/resource/SIO_000832">
        <rdfs:subClassOf rdf:resource="http://semanticscience.org/resource/SIO_000276"/>
        <terms:description xml:lang="en">negative emotion is an emotion that does not feel good.</terms:description>
        <rdfs:isDefinedBy rdf:resource="http://semanticscience.org/ontology/sio/v1.43/sio-subset-emotion.owl"/>
        <rdfs:label xml:lang="en">negative emotion</rdfs:label>
    </owl:Class>
    


    <!-- http://semanticscience.org/resource/SIO_000833 -->


    <owl:Class rdf:about="http://semanticscience.org/resource/SIO_000833">
        <rdfs:subClassOf rdf:resource="http://semanticscience.org/resource/SIO_000832"/>
        <terms:description xml:lang="en">Embarrassment is the emotion of intense discomfort with oneself, experienced upon having a socially unacceptable act or condition witnessed by or revealed to other.</terms:description>
        <rdfs:isDefinedBy rdf:resource="http://semanticscience.org/ontology/sio/v1.43/sio-subset-emotion.owl"/>
        <rdfs:label xml:lang="en">embarassment</rdfs:label>
    </owl:Class>
    


    <!-- http://semanticscience.org/resource/SIO_000834 -->


    <owl:Class rdf:about="http://semanticscience.org/resource/SIO_000834">
        <rdfs:subClassOf rdf:resource="http://semanticscience.org/resource/SIO_000832"/>
        <terms:description xml:lang="en">envy is an emotion that occurs when a person lacks another&apos;s (perceived) superior quality, achievement or possession and wishes that the other lacked it.</terms:description>
        <rdfs:isDefinedBy rdf:resource="http://semanticscience.org/ontology/sio/v1.43/sio-subset-emotion.owl"/>
        <rdfs:label xml:lang="en">envy</rdfs:label>
    </owl:Class>
    


    <!-- http://semanticscience.org/resource/SIO_000835 -->


    <owl:Class rdf:about="http://semanticscience.org/resource/SIO_000835">
        <rdfs:subClassOf rdf:resource="http://semanticscience.org/resource/SIO_000840"/>
        <terms:description xml:lang="en">euphoria is an emotion characterized by intense feelings of well-being, elation, happiness, ecstasy, excitement, and joy.</terms:description>
        <rdfs:isDefinedBy rdf:resource="http://semanticscience.org/ontology/sio/v1.43/sio-subset-emotion.owl"/>
        <rdfs:label xml:lang="en">euphoria</rdfs:label>
    </owl:Class>
    


    <!-- http://semanticscience.org/resource/SIO_000836 -->


    <owl:Class rdf:about="http://semanticscience.org/resource/SIO_000836">
        <rdfs:subClassOf rdf:resource="http://semanticscience.org/resource/SIO_000831"/>
        <terms:description xml:lang="en">excitement is a positive emotion of feeling great enthusiasm and eagerness.</terms:description>
        <rdfs:isDefinedBy rdf:resource="http://semanticscience.org/ontology/sio/v1.43/sio-subset-emotion.owl"/>
        <rdfs:label xml:lang="en">excitement</rdfs:label>
    </owl:Class>
    


    <!-- http://semanticscience.org/resource/SIO_000837 -->


    <owl:Class rdf:about="http://semanticscience.org/resource/SIO_000837">
        <rdfs:subClassOf rdf:resource="http://semanticscience.org/resource/SIO_000949"/>
        <terms:description xml:lang="en">Fear is a negative emotion induced by a perceived threat that induces one to hide or move quickly away from the location of the perceived threat.</terms:description>
        <rdfs:isDefinedBy rdf:resource="http://semanticscience.org/ontology/sio/v1.43/sio-subset-emotion.owl"/>
        <rdfs:label xml:lang="en">fear</rdfs:label>
    </owl:Class>
    


    <!-- http://semanticscience.org/resource/SIO_000838 -->


    <owl:Class rdf:about="http://semanticscience.org/resource/SIO_000838">
        <rdfs:subClassOf rdf:resource="http://semanticscience.org/resource/SIO_000814"/>
        <terms:description xml:lang="en">Frustration is an emotion that arises from the perceived resistance to the fulfillment of individual will. </terms:description>
        <rdfs:isDefinedBy rdf:resource="http://semanticscience.org/ontology/sio/v1.43/sio-subset-emotion.owl"/>
        <rdfs:label xml:lang="en">frustration</rdfs:label>
    </owl:Class>
    


    <!-- http://semanticscience.org/resource/SIO_000839 -->


    <owl:Class rdf:about="http://semanticscience.org/resource/SIO_000839">
        <rdfs:subClassOf rdf:resource="http://semanticscience.org/resource/SIO_000831"/>
        <terms:description xml:lang="en">Gratitude, thankfulness, gratefulness, or appreciation is a feeling, emotion or attitude in acknowledgment of a benefit that one has received or will receive.</terms:description>
        <resource:hasSynonym rdf:datatype="http://www.w3.org/2001/XMLSchema#string">appreciation</resource:hasSynonym>
        <resource:hasSynonym rdf:datatype="http://www.w3.org/2001/XMLSchema#string">gratefulness</resource:hasSynonym>
        <resource:hasSynonym rdf:datatype="http://www.w3.org/2001/XMLSchema#string">gratification</resource:hasSynonym>
        <resource:hasSynonym rdf:datatype="http://www.w3.org/2001/XMLSchema#string">thankfullness</resource:hasSynonym>
        <rdfs:isDefinedBy rdf:resource="http://semanticscience.org/ontology/sio/v1.43/sio-subset-emotion.owl"/>
        <rdfs:label xml:lang="en">gratitude</rdfs:label>
    </owl:Class>
    


    <!-- http://semanticscience.org/resource/SIO_000840 -->


    <owl:Class rdf:about="http://semanticscience.org/resource/SIO_000840">
        <rdfs:subClassOf rdf:resource="http://semanticscience.org/resource/SIO_000831"/>
        <terms:description xml:lang="en">happiness is an emotion characterized by positive or pleasant emotions ranging from contentment to intense joy.</terms:description>
        <rdfs:isDefinedBy rdf:resource="http://semanticscience.org/ontology/sio/v1.43/sio-subset-emotion.owl"/>
        <rdfs:label xml:lang="en">happiness</rdfs:label>
    </owl:Class>
    


    <!-- http://semanticscience.org/resource/SIO_000841 -->


    <owl:Class rdf:about="http://semanticscience.org/resource/SIO_000841">
        <rdfs:subClassOf rdf:resource="http://semanticscience.org/resource/SIO_000832"/>
        <terms:description xml:lang="en">Guilt is the emotion borne from feeling responsible for the commission of an offense and arises out of public humiliation.</terms:description>
        <resource:hasSynonym rdf:datatype="http://www.w3.org/2001/XMLSchema#string">guilty</resource:hasSynonym>
        <rdfs:isDefinedBy rdf:resource="http://semanticscience.org/ontology/sio/v1.43/sio-subset-emotion.owl"/>
        <rdfs:label xml:lang="en">guilt</rdfs:label>
    </owl:Class>
    


    <!-- http://semanticscience.org/resource/SIO_000842 -->


    <owl:Class rdf:about="http://semanticscience.org/resource/SIO_000842">
        <rdfs:subClassOf rdf:resource="http://semanticscience.org/resource/SIO_000863"/>
        <terms:description xml:lang="en">grief is an emotion in response to loss, whether physical or abstract including death, unemployment, ill health or the end of a relationship.</terms:description>
        <rdfs:isDefinedBy rdf:resource="http://semanticscience.org/ontology/sio/v1.43/sio-subset-emotion.owl"/>
        <rdfs:label xml:lang="en">grief</rdfs:label>
    </owl:Class>
    


    <!-- http://semanticscience.org/resource/SIO_000843 -->


    <owl:Class rdf:about="http://semanticscience.org/resource/SIO_000843">
        <rdfs:subClassOf rdf:resource="http://semanticscience.org/resource/SIO_000831"/>
        <terms:description xml:lang="en">hope is an emotion of belief in a positive outcome related to events and circumstances in one&apos;s life.</terms:description>
        <rdfs:isDefinedBy rdf:resource="http://semanticscience.org/ontology/sio/v1.43/sio-subset-emotion.owl"/>
        <rdfs:label xml:lang="en">hope</rdfs:label>
    </owl:Class>
    


    <!-- http://semanticscience.org/resource/SIO_000844 -->


    <owl:Class rdf:about="http://semanticscience.org/resource/SIO_000844">
        <rdfs:subClassOf rdf:resource="http://semanticscience.org/resource/SIO_000832"/>
        <terms:description xml:lang="en">Hostility is the intense negative emotion of being in conflict or opposition to someone or something.</terms:description>
        <rdfs:isDefinedBy rdf:resource="http://semanticscience.org/ontology/sio/v1.43/sio-subset-emotion.owl"/>
        <rdfs:label xml:lang="en">hostility</rdfs:label>
    </owl:Class>
    


    <!-- http://semanticscience.org/resource/SIO_000845 -->


    <owl:Class rdf:about="http://semanticscience.org/resource/SIO_000845">
        <rdfs:subClassOf rdf:resource="http://semanticscience.org/resource/SIO_000832"/>
        <terms:description xml:lang="en">hurt is an unpleasant feeling, emotion or sensation.</terms:description>
        <rdfs:isDefinedBy rdf:resource="http://semanticscience.org/ontology/sio/v1.43/sio-subset-emotion.owl"/>
        <rdfs:label xml:lang="en">hurt</rdfs:label>
    </owl:Class>
    


    <!-- http://semanticscience.org/resource/SIO_000846 -->


    <owl:Class rdf:about="http://semanticscience.org/resource/SIO_000846">
        <rdfs:subClassOf rdf:resource="http://semanticscience.org/resource/SIO_000832"/>
        <terms:description xml:lang="en">Hysteria is an unmanageable emotion.</terms:description>
        <rdfs:isDefinedBy rdf:resource="http://semanticscience.org/ontology/sio/v1.43/sio-subset-emotion.owl"/>
        <rdfs:label xml:lang="en">hysteria</rdfs:label>
    </owl:Class>
    


    <!-- http://semanticscience.org/resource/SIO_000847 -->


    <owl:Class rdf:about="http://semanticscience.org/resource/SIO_000847">
        <rdfs:subClassOf rdf:resource="http://semanticscience.org/resource/SIO_000276"/>
        <terms:description xml:lang="en">indifference is an emotion characterized by lack of interest, concern, or sympathy.</terms:description>
        <rdfs:isDefinedBy rdf:resource="http://semanticscience.org/ontology/sio/v1.43/sio-subset-emotion.owl"/>
        <rdfs:label xml:lang="en">indifference</rdfs:label>
    </owl:Class>
    


    <!-- http://semanticscience.org/resource/SIO_000848 -->


    <owl:Class rdf:about="http://semanticscience.org/resource/SIO_000848">
        <rdfs:subClassOf rdf:resource="http://semanticscience.org/resource/SIO_000831"/>
        <terms:description xml:lang="en">interest is the emotion of wanting to know or learn about something or someone.</terms:description>
        <rdfs:isDefinedBy rdf:resource="http://semanticscience.org/ontology/sio/v1.43/sio-subset-emotion.owl"/>
        <rdfs:label xml:lang="en">interest</rdfs:label>
    </owl:Class>
    


    <!-- http://semanticscience.org/resource/SIO_000849 -->


    <owl:Class rdf:about="http://semanticscience.org/resource/SIO_000849">
        <rdfs:subClassOf rdf:resource="http://semanticscience.org/resource/SIO_000834"/>
        <terms:description xml:lang="en">jealousy is an emotion and typically refers to the negative thoughts and feelings of insecurity, fear, and anxiety over an anticipated loss of something that the person values, particularly in reference to a human connection.</terms:description>
        <rdfs:isDefinedBy rdf:resource="http://semanticscience.org/ontology/sio/v1.43/sio-subset-emotion.owl"/>
        <rdfs:label xml:lang="en">jealousy</rdfs:label>
    </owl:Class>
    


    <!-- http://semanticscience.org/resource/SIO_000850 -->


    <owl:Class rdf:about="http://semanticscience.org/resource/SIO_000850">
        <rdfs:subClassOf rdf:resource="http://semanticscience.org/resource/SIO_000840"/>
        <terms:description xml:lang="en">joy is an emotion of intense happiness.</terms:description>
        <rdfs:isDefinedBy rdf:resource="http://semanticscience.org/ontology/sio/v1.43/sio-subset-emotion.owl"/>
        <rdfs:label xml:lang="en">joy</rdfs:label>
    </owl:Class>
    


    <!-- http://semanticscience.org/resource/SIO_000851 -->


    <owl:Class rdf:about="http://semanticscience.org/resource/SIO_000851">
        <rdfs:subClassOf rdf:resource="http://semanticscience.org/resource/SIO_000828"/>
        <terms:description xml:lang="en">loathing is an intense dislike or disgust.</terms:description>
        <rdfs:isDefinedBy rdf:resource="http://semanticscience.org/ontology/sio/v1.43/sio-subset-emotion.owl"/>
        <rdfs:label xml:lang="en">loathing</rdfs:label>
    </owl:Class>
    


    <!-- http://semanticscience.org/resource/SIO_000852 -->


    <owl:Class rdf:about="http://semanticscience.org/resource/SIO_000852">
        <rdfs:subClassOf rdf:resource="http://semanticscience.org/resource/SIO_000832"/>
        <terms:description xml:lang="en">Loneliness is an unpleasant emotion in which a person feels a strong sense of emptiness, yearning distress and solitude resulting from inadequate quantity or quality of social relationships.</terms:description>
        <rdfs:isDefinedBy rdf:resource="http://semanticscience.org/ontology/sio/v1.43/sio-subset-emotion.owl"/>
        <rdfs:label xml:lang="en">loneliness</rdfs:label>
    </owl:Class>
    


    <!-- http://semanticscience.org/resource/SIO_000853 -->


    <owl:Class rdf:about="http://semanticscience.org/resource/SIO_000853">
        <rdfs:subClassOf rdf:resource="http://semanticscience.org/resource/SIO_000825"/>
        <terms:description xml:lang="en">lust is the strong desire for sex.</terms:description>
        <rdfs:isDefinedBy rdf:resource="http://semanticscience.org/ontology/sio/v1.43/sio-subset-emotion.owl"/>
        <rdfs:label xml:lang="en">lust</rdfs:label>
    </owl:Class>
    


    <!-- http://semanticscience.org/resource/SIO_000854 -->


    <owl:Class rdf:about="http://semanticscience.org/resource/SIO_000854">
        <rdfs:subClassOf rdf:resource="http://semanticscience.org/resource/SIO_000863"/>
        <terms:description xml:lang="en">misery is a feeling of great unhappiness, suffering and/or pain.</terms:description>
        <rdfs:isDefinedBy rdf:resource="http://semanticscience.org/ontology/sio/v1.43/sio-subset-emotion.owl"/>
        <rdfs:label xml:lang="en">misery</rdfs:label>
    </owl:Class>
    


    <!-- http://semanticscience.org/resource/SIO_000855 -->


    <owl:Class rdf:about="http://semanticscience.org/resource/SIO_000855">
        <rdfs:subClassOf rdf:resource="http://semanticscience.org/resource/SIO_000837"/>
        <terms:description xml:lang="en">Panic is a sudden emotion of fear which is so strong as to dominate or prevent reason and logical thinking, replacing it with overwhelming feelings of anxiety and frantic agitation consistent with an animalistic fight-or-flight reaction.</terms:description>
        <rdfs:isDefinedBy rdf:resource="http://semanticscience.org/ontology/sio/v1.43/sio-subset-emotion.owl"/>
        <rdfs:label xml:lang="en">panic</rdfs:label>
    </owl:Class>
    


    <!-- http://semanticscience.org/resource/SIO_000856 -->


    <owl:Class rdf:about="http://semanticscience.org/resource/SIO_000856">
        <rdfs:subClassOf rdf:resource="http://semanticscience.org/resource/SIO_000825"/>
        <terms:description xml:lang="en">passion is the intense desire for something.</terms:description>
        <rdfs:isDefinedBy rdf:resource="http://semanticscience.org/ontology/sio/v1.43/sio-subset-emotion.owl"/>
        <rdfs:label xml:lang="en">passion</rdfs:label>
    </owl:Class>
    


    <!-- http://semanticscience.org/resource/SIO_000857 -->


    <owl:Class rdf:about="http://semanticscience.org/resource/SIO_000857">
        <rdfs:subClassOf rdf:resource="http://semanticscience.org/resource/SIO_000832"/>
        <terms:description xml:lang="en">Pity is the emotion of sadness or sorrow for another.</terms:description>
        <rdfs:isDefinedBy rdf:resource="http://semanticscience.org/ontology/sio/v1.43/sio-subset-emotion.owl"/>
        <rdfs:label xml:lang="en">pity</rdfs:label>
    </owl:Class>
    


    <!-- http://semanticscience.org/resource/SIO_000858 -->


    <owl:Class rdf:about="http://semanticscience.org/resource/SIO_000858">
        <rdfs:subClassOf rdf:resource="http://semanticscience.org/resource/SIO_000840"/>
        <terms:description xml:lang="en">pleasure is an emotion of happy satisfaction and enjoyment.</terms:description>
        <rdfs:isDefinedBy rdf:resource="http://semanticscience.org/ontology/sio/v1.43/sio-subset-emotion.owl"/>
        <rdfs:label xml:lang="en">pleasure</rdfs:label>
    </owl:Class>
    


    <!-- http://semanticscience.org/resource/SIO_000859 -->


    <owl:Class rdf:about="http://semanticscience.org/resource/SIO_000859">
        <rdfs:subClassOf rdf:resource="http://semanticscience.org/resource/SIO_000864"/>
        <terms:description xml:lang="en">pride is an emotion of satisfaction of attachment toward one&apos;s own or another&apos;s choices and actions, or toward a whole group of people, and is a product of praise, independent self-reflection, or a fulfilled feeling of belonging.</terms:description>
        <rdfs:isDefinedBy rdf:resource="http://semanticscience.org/ontology/sio/v1.43/sio-subset-emotion.owl"/>
        <rdfs:label xml:lang="en">pride</rdfs:label>
    </owl:Class>
    


    <!-- http://semanticscience.org/resource/SIO_000860 -->


    <owl:Class rdf:about="http://semanticscience.org/resource/SIO_000860">
        <rdfs:subClassOf rdf:resource="http://semanticscience.org/resource/SIO_000410"/>
        <terms:description xml:lang="en">Rage is a feeling of intense anger that is associated with the Fight-or-flight response.</terms:description>
        <rdfs:isDefinedBy rdf:resource="http://semanticscience.org/ontology/sio/v1.43/sio-subset-emotion.owl"/>
        <rdfs:label xml:lang="en">rage</rdfs:label>
    </owl:Class>
    


    <!-- http://semanticscience.org/resource/SIO_000861 -->


    <owl:Class rdf:about="http://semanticscience.org/resource/SIO_000861">
        <rdfs:subClassOf rdf:resource="http://semanticscience.org/resource/SIO_000873"/>
        <terms:description xml:lang="en">regret is a feeling of sadness, repentance, or disappointment over something that has happened or been done.</terms:description>
        <rdfs:isDefinedBy rdf:resource="http://semanticscience.org/ontology/sio/v1.43/sio-subset-emotion.owl"/>
        <rdfs:label xml:lang="en">regret</rdfs:label>
    </owl:Class>
    


    <!-- http://semanticscience.org/resource/SIO_000862 -->


    <owl:Class rdf:about="http://semanticscience.org/resource/SIO_000862">
        <rdfs:subClassOf rdf:resource="http://semanticscience.org/resource/SIO_000861"/>
        <terms:description xml:lang="en">remorse is an emotion of personal regret felt by a person after he or she has committed an act which they deem to be shameful, hurtful, or violent.</terms:description>
        <rdfs:isDefinedBy rdf:resource="http://semanticscience.org/ontology/sio/v1.43/sio-subset-emotion.owl"/>
        <rdfs:label xml:lang="en">remorse</rdfs:label>
    </owl:Class>
    


    <!-- http://semanticscience.org/resource/SIO_000863 -->


    <owl:Class rdf:about="http://semanticscience.org/resource/SIO_000863">
        <rdfs:subClassOf rdf:resource="http://semanticscience.org/resource/SIO_000832"/>
        <terms:description xml:lang="en">sadness is emotional pain associated with, or characterized by feelings of disadvantage, loss, despair, helplessness, sorrow, and rage.</terms:description>
        <resource:hasSynonym rdf:datatype="http://www.w3.org/2001/XMLSchema#string">sad</resource:hasSynonym>
        <resource:hasSynonym rdf:datatype="http://www.w3.org/2001/XMLSchema#string">unhappiness</resource:hasSynonym>
        <resource:hasSynonym rdf:datatype="http://www.w3.org/2001/XMLSchema#string">unhappy</resource:hasSynonym>
        <rdfs:isDefinedBy rdf:resource="http://semanticscience.org/ontology/sio/v1.43/sio-subset-emotion.owl"/>
        <rdfs:label xml:lang="en">sadness</rdfs:label>
    </owl:Class>
    


    <!-- http://semanticscience.org/resource/SIO_000864 -->


    <owl:Class rdf:about="http://semanticscience.org/resource/SIO_000864">
        <rdfs:subClassOf rdf:resource="http://semanticscience.org/resource/SIO_000822"/>
        <terms:description xml:lang="en">satisfaction is an emotion of fulfillment of one&apos;s wishes, expectations, or needs, or the pleasure derived from this.</terms:description>
        <rdfs:isDefinedBy rdf:resource="http://semanticscience.org/ontology/sio/v1.43/sio-subset-emotion.owl"/>
        <rdfs:label xml:lang="en">satisfaction</rdfs:label>
    </owl:Class>
    


    <!-- http://semanticscience.org/resource/SIO_000865 -->


    <owl:Class rdf:about="http://semanticscience.org/resource/SIO_000865">
        <rdfs:subClassOf rdf:resource="http://semanticscience.org/resource/SIO_000832"/>
        <terms:description xml:lang="en">shame is the emotion borne from feeling responsible for the commission of an offense.</terms:description>
        <rdfs:isDefinedBy rdf:resource="http://semanticscience.org/ontology/sio/v1.43/sio-subset-emotion.owl"/>
        <rdfs:label xml:lang="en">shame</rdfs:label>
    </owl:Class>
    


    <!-- http://semanticscience.org/resource/SIO_000866 -->


    <owl:Class rdf:about="http://semanticscience.org/resource/SIO_000866">
        <rdfs:subClassOf rdf:resource="http://semanticscience.org/resource/SIO_000832"/>
        <terms:description xml:lang="en">shock is an emotion of sudden upset or surprise.</terms:description>
        <rdfs:isDefinedBy rdf:resource="http://semanticscience.org/ontology/sio/v1.43/sio-subset-emotion.owl"/>
        <rdfs:label xml:lang="en">shock</rdfs:label>
    </owl:Class>
    


    <!-- http://semanticscience.org/resource/SIO_000867 -->


    <owl:Class rdf:about="http://semanticscience.org/resource/SIO_000867">
        <rdfs:subClassOf rdf:resource="http://semanticscience.org/resource/SIO_000832"/>
        <terms:description xml:lang="en">shyness is an emotion of apprehension, lack of comfort, or awkwardness experienced when in proximity to, approaching, or being approached by other individuals, especially in new situations or with unfamiliar individuals.</terms:description>
        <rdfs:isDefinedBy rdf:resource="http://semanticscience.org/ontology/sio/v1.43/sio-subset-emotion.owl"/>
        <rdfs:label xml:lang="en">shyness</rdfs:label>
    </owl:Class>
    


    <!-- http://semanticscience.org/resource/SIO_000868 -->


    <owl:Class rdf:about="http://semanticscience.org/resource/SIO_000868">
        <rdfs:subClassOf rdf:resource="http://semanticscience.org/resource/SIO_000863"/>
        <terms:description xml:lang="en">sorrow is the emotion that is characterized by a long term state of intense sadness, distress and a degree of resignation (not accepting).</terms:description>
        <rdfs:isDefinedBy rdf:resource="http://semanticscience.org/ontology/sio/v1.43/sio-subset-emotion.owl"/>
        <rdfs:label xml:lang="en">sorrow</rdfs:label>
    </owl:Class>
    


    <!-- http://semanticscience.org/resource/SIO_000869 -->


    <owl:Class rdf:about="http://semanticscience.org/resource/SIO_000869">
        <rdfs:subClassOf rdf:resource="http://semanticscience.org/resource/SIO_000845"/>
        <terms:description xml:lang="en">Suffering is the unpleasant emotion and aversion associated with the perception of harm or threat of harm in an individual.</terms:description>
        <rdfs:isDefinedBy rdf:resource="http://semanticscience.org/ontology/sio/v1.43/sio-subset-emotion.owl"/>
        <rdfs:label xml:lang="en">suffering</rdfs:label>
    </owl:Class>
    


    <!-- http://semanticscience.org/resource/SIO_000870 -->


    <owl:Class rdf:about="http://semanticscience.org/resource/SIO_000870">
        <rdfs:subClassOf rdf:resource="http://semanticscience.org/resource/SIO_000831"/>
        <terms:description xml:lang="en">surprise is a brief emotion experienced as the result of an unexpected event. </terms:description>
        <rdfs:isDefinedBy rdf:resource="http://semanticscience.org/ontology/sio/v1.43/sio-subset-emotion.owl"/>
        <rdfs:label xml:lang="en">surprise</rdfs:label>
    </owl:Class>
    


    <!-- http://semanticscience.org/resource/SIO_000871 -->


    <owl:Class rdf:about="http://semanticscience.org/resource/SIO_000871">
        <rdfs:subClassOf rdf:resource="http://semanticscience.org/resource/SIO_000829"/>
        <terms:description xml:lang="en">terror is the extreme feeling of fear.</terms:description>
        <rdfs:isDefinedBy rdf:resource="http://semanticscience.org/ontology/sio/v1.43/sio-subset-emotion.owl"/>
        <rdfs:label xml:lang="en">terror</rdfs:label>
    </owl:Class>
    


    <!-- http://semanticscience.org/resource/SIO_000872 -->


    <owl:Class rdf:about="http://semanticscience.org/resource/SIO_000872">
        <rdfs:subClassOf rdf:resource="http://semanticscience.org/resource/SIO_000870"/>
        <terms:description xml:lang="en">wonder is an emotion of perceiving something very rare or unexpected, but not threatening.</terms:description>
        <rdfs:isDefinedBy rdf:resource="http://semanticscience.org/ontology/sio/v1.43/sio-subset-emotion.owl"/>
        <rdfs:label xml:lang="en">wonder</rdfs:label>
    </owl:Class>
    


    <!-- http://semanticscience.org/resource/SIO_000873 -->


    <owl:Class rdf:about="http://semanticscience.org/resource/SIO_000873">
        <rdfs:subClassOf rdf:resource="http://semanticscience.org/resource/SIO_000949"/>
        <terms:description xml:lang="en">worry is the emotion characterized by concer over a real or imaginary issue.</terms:description>
        <rdfs:isDefinedBy rdf:resource="http://semanticscience.org/ontology/sio/v1.43/sio-subset-emotion.owl"/>
        <rdfs:label xml:lang="en">worry</rdfs:label>
    </owl:Class>
    


    <!-- http://semanticscience.org/resource/SIO_000949 -->


    <owl:Class rdf:about="http://semanticscience.org/resource/SIO_000949">
        <rdfs:subClassOf rdf:resource="http://semanticscience.org/resource/SIO_000832"/>
        <terms:description xml:lang="en">apprehension is the negative emotion that something unpleasant will occur.</terms:description>
        <rdfs:isDefinedBy rdf:resource="http://semanticscience.org/ontology/sio/v1.43/sio-subset-emotion.owl"/>
        <rdfs:label xml:lang="en">apprehension</rdfs:label>
    </owl:Class>
    


    <!-- http://semanticscience.org/resource/SIO_000950 -->


    <owl:Class rdf:about="http://semanticscience.org/resource/SIO_000950">
        <rdfs:subClassOf rdf:resource="http://semanticscience.org/resource/SIO_000828"/>
        <terms:description xml:lang="en">resentment is disgust directed toward a higher status individual.</terms:description>
        <rdfs:isDefinedBy rdf:resource="http://semanticscience.org/ontology/sio/v1.43/sio-subset-emotion.owl"/>
        <rdfs:label xml:lang="en">resentment</rdfs:label>
    </owl:Class>
    


    <!-- http://semanticscience.org/resource/SIO_000951 -->


    <owl:Class rdf:about="http://semanticscience.org/resource/SIO_000951">
        <rdfs:subClassOf rdf:resource="http://semanticscience.org/resource/SIO_000845"/>
        <terms:description xml:lang="en">Pain is an unpleasant sensory and emotional experience associated with actual or potential tissue damage, or described in terms of such damage.</terms:description>
        <rdfs:isDefinedBy rdf:resource="http://semanticscience.org/ontology/sio/v1.43/sio-subset-emotion.owl"/>
        <rdfs:label xml:lang="en">pain</rdfs:label>
    </owl:Class>
    


    <!-- http://semanticscience.org/resource/SIO_001195 -->


    <owl:Class rdf:about="http://semanticscience.org/resource/SIO_001195">
        <rdfs:subClassOf rdf:resource="http://semanticscience.org/resource/SIO_000006"/>
        <terms:description xml:lang="en">Behaviour is the set of actions and mannerisms made by systems (biological or otherwise) in response to stimuli or inputs, whether internal or external, conscious or subconscious, overt or covert, and voluntary or involuntary.</terms:description>
        <resource:subset rdf:datatype="http://www.w3.org/2001/XMLSchema#string">behaviour+</resource:subset>
        <resource:subset rdf:datatype="http://www.w3.org/2001/XMLSchema#string">core</resource:subset>
        <rdfs:isDefinedBy rdf:resource="http://semanticscience.org/ontology/sio/v1.43/sio-subset-emotion.owl"/>
        <rdfs:label xml:lang="en">behaviour</rdfs:label>
    </owl:Class>
    


    <!-- http://semanticscience.org/resource/SIO_001281 -->


    <owl:Class rdf:about="http://semanticscience.org/resource/SIO_001281">
        <rdfs:subClassOf rdf:resource="http://semanticscience.org/resource/SIO_000845"/>
        <terms:description rdf:datatype="http://www.w3.org/2001/XMLSchema#string">Humiliation is the abasement of pride, which creates mortification or leads to a state of being humbled or reduced to lowliness or submission.</terms:description>
        <rdfs:isDefinedBy rdf:resource="http://semanticscience.org/ontology/sio/v1.43/sio-subset-emotion.owl"/>
        <rdfs:label xml:lang="en">humiliation</rdfs:label>
    </owl:Class>
    


    <!-- http://semanticscience.org/resource/SIO_001282 -->


    <owl:Class rdf:about="http://semanticscience.org/resource/SIO_001282">
        <rdfs:subClassOf rdf:resource="http://semanticscience.org/resource/SIO_000832"/>
        <terms:description rdf:datatype="http://www.w3.org/2001/XMLSchema#string">hunger is the craving for food.</terms:description>
        <rdfs:isDefinedBy rdf:resource="http://semanticscience.org/ontology/sio/v1.43/sio-subset-emotion.owl"/>
        <rdfs:label xml:lang="en">hunger</rdfs:label>
    </owl:Class>
    


    <!-- http://semanticscience.org/resource/SIO_001283 -->


    <owl:Class rdf:about="http://semanticscience.org/resource/SIO_001283">
        <rdfs:subClassOf rdf:resource="http://semanticscience.org/resource/SIO_000832"/>
        <terms:description rdf:datatype="http://www.w3.org/2001/XMLSchema#string">Discouragement is the emtion of having lost confidence or enthusiasm.</terms:description>
        <resource:hasSynonym rdf:datatype="http://www.w3.org/2001/XMLSchema#string">discouraged</resource:hasSynonym>
        <rdfs:isDefinedBy rdf:resource="http://semanticscience.org/ontology/sio/v1.43/sio-subset-emotion.owl"/>
        <rdfs:label xml:lang="en">discouragement</rdfs:label>
    </owl:Class>
    


    <!-- http://semanticscience.org/resource/SIO_001284 -->


    <owl:Class rdf:about="http://semanticscience.org/resource/SIO_001284">
        <rdfs:subClassOf rdf:resource="http://semanticscience.org/resource/SIO_000831"/>
        <terms:description rdf:datatype="http://www.w3.org/2001/XMLSchema#string">satisfaction is the emotion of fulfillling one&apos;s wishes, expectations, or needs.</terms:description>
        <resource:hasSynonym rdf:datatype="http://www.w3.org/2001/XMLSchema#string">contentment</resource:hasSynonym>
        <resource:hasSynonym rdf:datatype="http://www.w3.org/2001/XMLSchema#string">pleasure</resource:hasSynonym>
        <rdfs:isDefinedBy rdf:resource="http://semanticscience.org/ontology/sio/v1.43/sio-subset-emotion.owl"/>
        <rdfs:label xml:lang="en">satisfaction</rdfs:label>
    </owl:Class>
    


    <!-- http://semanticscience.org/resource/SIO_001285 -->


    <owl:Class rdf:about="http://semanticscience.org/resource/SIO_001285">
        <rdfs:subClassOf rdf:resource="http://semanticscience.org/resource/SIO_000832"/>
        <terms:description rdf:datatype="http://www.w3.org/2001/XMLSchema#string">suicidal is the emotion of being deeply unhappy or depressed with thoughts of killing one&apos;s self.</terms:description>
        <rdfs:isDefinedBy rdf:resource="http://semanticscience.org/ontology/sio/v1.43/sio-subset-emotion.owl"/>
        <rdfs:label xml:lang="en">suicidal</rdfs:label>
    </owl:Class>
    


    <!-- http://semanticscience.org/resource/SIO_001286 -->


    <owl:Class rdf:about="http://semanticscience.org/resource/SIO_001286">
        <rdfs:subClassOf rdf:resource="http://semanticscience.org/resource/SIO_000832"/>
        <terms:description rdf:datatype="http://www.w3.org/2001/XMLSchema#string">irritability is the negative emotion of quick excitability to annoyance, impatience, or anger.</terms:description>
        <resource:hasSynonym rdf:datatype="http://www.w3.org/2001/XMLSchema#string">irritable</resource:hasSynonym>
        <rdfs:isDefinedBy rdf:resource="http://semanticscience.org/ontology/sio/v1.43/sio-subset-emotion.owl"/>
        <rdfs:label xml:lang="en">irritability</rdfs:label>
    </owl:Class>
    


    <!-- http://semanticscience.org/resource/SIO_001287 -->


    <owl:Class rdf:about="http://semanticscience.org/resource/SIO_001287">
        <rdfs:subClassOf rdf:resource="http://semanticscience.org/resource/SIO_000832"/>
        <terms:description rdf:datatype="http://www.w3.org/2001/XMLSchema#string">indecision is the emotion of being unable to choose between two or more possible courses of action.</terms:description>
        <resource:hasSynonym rdf:datatype="http://www.w3.org/2001/XMLSchema#string">indecisiveness</resource:hasSynonym>
        <rdfs:isDefinedBy rdf:resource="http://semanticscience.org/ontology/sio/v1.43/sio-subset-emotion.owl"/>
        <rdfs:label xml:lang="en">indecision</rdfs:label>
    </owl:Class>
    


    <!-- 
    ///////////////////////////////////////////////////////////////////////////////////////
    //
    // Annotations
    //
    ///////////////////////////////////////////////////////////////////////////////////////
     -->


    <rdf:Description rdf:about="http://semanticscience.org/ontology/sio.owl">
        <rdfs:isDefinedBy rdf:resource="http://semanticscience.org/ontology/sio/v1.43/sio-subset-emotion.owl"/>
        <owl:versionInfo rdf:datatype="http://www.w3.org/2001/XMLSchema#string">sio-subset-emotion.owl</owl:versionInfo>
    </rdf:Description>
</rdf:RDF>



<!-- Generated by the OWL API (version 5.1.0) https://github.com/owlcs/owlapi/ -->


